SystemVerilog/TheFerryman/ferryman/src/ferryman.sv
module ferryman(
    input clk, 
    input w, g, c);
    //In the start state, everyone is on same slide of river
    reg bank_w = 0; //Wolf
    reg bank_g = 0; //Goat
    reg bank_c = 0; //Cabbage
    reg bank_m = 0; //Boatman

    always @(posedge clk) begin
        // Can ship atmost one object at each clock
        assume (w+g+c <= 1);

        bank_m <= !bank_m;

        if (w && (bank_w == bank_m)) bank_w <= !bank_m;
        if (g && (bank_g == bank_m)) bank_g <= !bank_m;
        if (c && (bank_c == bank_m)) bank_c <= !bank_m;
        // Wolf and goat shouldn't be left together goat without Boatman  
        if (bank_w != bank_m) begin
            assume (bank_w != bank_g);
        end
        // Goat shouldn't be left together cabbage without Boatman  
        if (bank_g != bank_m) begin
            assume (bank_g != bank_c);
        end
    // Safely cross the river
    cover (bank_w && bank_g && bank_c);

    end    
    
endmodule

SystemVerilog/TheFerryman/ferryman/engine_0/trace0.vcd
$version Generated by Yosys-SMTBMC $end
$timescale 1ns $end
$var integer 32 t smt_step $end
$var event 1 ! smt_clock $end
$scope module ferryman $end
$var wire 1 n0 bank_c $end
$var wire 1 n1 bank_g $end
$var wire 1 n2 bank_m $end
$var wire 1 n3 bank_w $end
$var wire 1 n4 c $end
$var wire 1 n5 clk $end
$var wire 1 n6 g $end
$var wire 1 n7 w $end
$upscope $end
$enddefinitions $end
#0
1!
b00000000000000000000000000000000 t
b1 n5
b0 n0
b0 n1
b0 n2
b0 n3
b0 n4
b1 n6
b0 n7
#5
b0 n5
#10
1!
b00000000000000000000000000000001 t
b1 n5
b0 n0
b1 n1
b1 n2
b0 n3
b0 n4
b0 n6
b0 n7
#15
b0 n5
#20
1!
b00000000000000000000000000000010 t
b1 n5
b0 n0
b1 n1
b0 n2
b0 n3
b1 n4
b0 n6
b0 n7
#25
b0 n5
#30
1!
b00000000000000000000000000000011 t
b1 n5
b1 n0
b1 n1
b1 n2
b0 n3
b0 n4
b1 n6
b0 n7
#35
b0 n5
#40
1!
b00000000000000000000000000000100 t
b1 n5
b1 n0
b0 n1
b0 n2
b0 n3
b0 n4
b0 n6
b1 n7
#45
b0 n5
#50
1!
b00000000000000000000000000000101 t
b1 n5
b1 n0
b0 n1
b1 n2
b1 n3
b0 n4
b1 n6
b0 n7
#55
b0 n5
#60
1!
b00000000000000000000000000000110 t
b1 n5
b1 n0
b0 n1
b0 n2
b1 n3
b0 n4
b1 n6
b0 n7
#65
b0 n5
#70
1!
b00000000000000000000000000000111 t
b1 n5
b1 n0
b1 n1
b1 n2
b1 n3
b0 n4
b1 n6
b0 n7
#75
b0 n5
#80
1!
b00000000000000000000000000001000 t
b1 n5
b1 n0
b0 n1
b0 n2
b1 n3
b0 n4
b0 n6
b0 n7
#85
b0 n5
#90
1!
b00000000000000000000000000001001 t
b1 n5
